fontsplitta/__init__.py
fontsplitta/__main__.py
fontsplitta/google_fonts.py
fontsplitta/split.py
fontsplitta/test_server.py
fontsplitta-0.1.6.dist-info/METADATA
fontsplitta-0.1.6.dist-info/WHEEL
fontsplitta-0.1.6.dist-info/entry_points.txt
fontsplitta-0.1.6.dist-info/licenses/LICENSE
fontsplitta-0.1.6.dist-info/RECORD
