Metadata-Version: 2.4
Name: fontsplitta
Version: 0.1.6
Summary: fontsplitta is a command-line tool that splits web fonts and generates CSS.
Author-email: shunirr <git@s5r.jp>
License: MIT
License-File: LICENSE
Requires-Python: <3.12,>=3.11
Requires-Dist: brotli>=1.1.0
Requires-Dist: click>=8.1.8
Requires-Dist: fonttools>=4.56.0
Requires-Dist: urllib3>=2.3.0
Provides-Extra: dev
Requires-Dist: pyinstaller>=6.12.0; extra == 'dev'
Requires-Dist: setuptools>=75.8.2; extra == 'dev'
